trafficlight/__init__.py
trafficlight/main.py
trafficlight-1.4.7.dist-info/LICENSE
trafficlight-1.4.7.dist-info/METADATA
trafficlight-1.4.7.dist-info/WHEEL
trafficlight-1.4.7.dist-info/entry_points.txt
trafficlight-1.4.7.dist-info/top_level.txt
trafficlight-1.4.7.dist-info/RECORD
