Metadata-Version: 2.1
Name: trafficlight
Version: 1.4.7
Summary: Start and stop EC2s using tags. now in color!
Home-page: https://bitbucket.org/rednap/trafficlight
Author: Andy Klier
Author-email: andyklier@gmail.com
License: UNKNOWN
Platform: UNKNOWN
Classifier: Programming Language :: Python :: 3
Classifier: License :: OSI Approved :: MIT License
Classifier: Operating System :: OS Independent
Requires-Python: >=3.6
Requires-Dist: setuptools
Requires-Dist: string-color (>=0.2.7)
Requires-Dist: inquirer
